{
  "tests": [
    {
      "name": "npm test",
      "setup": "npm ci",
      "run": "npm test",
      "input": "",
      "output": "",
      "comparison": "exact",
      "timeout": 10,
      "points": 1
    },
    {
      "name": "npm run typecheck",
      "setup": "npm ci",
      "run": "npm run typecheck",
      "input": "",
      "output": "",
      "comparison": "exact",
      "timeout": 10,
      "points": 1
    },
    {
      "name": "npm run lint",
      "setup": "npm ci",
      "run": "npm run lint",
      "input": "",
      "output": "",
      "comparison": "exact",
      "timeout": 10,
      "points": 1
    }
  ]
}